[
  {
    "Author": "rekyuu",
    "Name": "StanleyParableXiv",
    "Description": "Witty commentary to the brilliant things you do.",
    "InternalName": "StanleyParableXiv",
    "AssemblyVersion": "1.0.0.0",
    "TestingAssemblyVersion": "1.0.0.0",
    "RepoUrl": "https://github.com/rekyuu/StanleyParableXiv",
    "ApplicableVersion": "any",
    "DalamudApiLevel": 8,
    "IsHide": "False",
    "IsTestingExclusive": "False",
    "DownloadCount": 0,
    "LastUpdate": 0,
    "LoadPriority": 69420,
    "LoadRequiredState": 2,
    "LoadSync": true,
    "DownloadLinkInstall": "https://github.com/rekyuu/StanleyParableXiv/releases/download/1.0.0.0/StanleyParableXiv.zip",
    "DownloadLinkTesting": "https://github.com/rekyuu/StanleyParableXiv/releases/download/1.0.0.0/StanleyParableXiv.zip",
    "DownloadLinkUpdate": "https://github.com/rekyuu/StanleyParableXiv/releases/download/1.0.0.0/StanleyParableXiv.zip",
    "IconUrl": "https://raw.githubusercontent.com/rekyuu/StanleyParableXiv/main/images/icon.png"
  }
]